leanda/__init__.py
leanda/api.py
leanda/cli.py
leanda/config.py
leanda/endpoint_helper.py
leanda/filelist_helper.py
leanda/leanda.py
leanda/parser_helper.py
leanda/commands/__init__.py
leanda/commands/browse.py
leanda/commands/categories.py
leanda/commands/convert.py
leanda/commands/download.py
leanda/commands/list_items.py
leanda/commands/livesync.py
leanda/commands/login.py
leanda/commands/models.py
leanda/commands/predict.py
leanda/commands/recordsets.py
leanda/commands/train.py
leanda/commands/upload.py
leanda-0.0.3.data/scripts/leanda
leanda-0.0.3.data/scripts/leanda.cmd
leanda-0.0.3.dist-info/LICENSE
leanda-0.0.3.dist-info/METADATA
leanda-0.0.3.dist-info/WHEEL
leanda-0.0.3.dist-info/top_level.txt
leanda-0.0.3.dist-info/RECORD
