Metadata-Version: 2.1
Name: leanda
Version: 0.0.3
Summary: Leanda Command Line Interface
Home-page: https://github.com/ArqiSoft/leanda-cli
Author: ArqiSoft
Author-email: info@arqisoft.com
License: UNKNOWN
Platform: UNKNOWN
Classifier: Programming Language :: Python :: 3
Classifier: License :: OSI Approved :: GNU General Public License v3 or later (GPLv3+)
Classifier: Operating System :: OS Independent
